toolos/__init__.py
toolos/api.py
toolos/data/lang/de.json
toolos/data/lang/en.json
toolos/data/lang/es.json
toolos/data/lang/fr.json
toolos/data/lang/ru.json
toolos/data/lang/sv.json
toolos/data/lang/tr.json
toolos/frameworks/pyqt.py
toolos/frameworks/ursinaengine.py
toolos/lib/objects.py
toolos/lib/assets/ai.py
toolos/lib/assets/cli.py
toolos/lib/assets/cons.py
toolos/lib/assets/filewriter.py
toolos/lib/assets/gipeo.py
toolos/lib/assets/sqlsave.py
toolos/lib/assets/statemachine.py
toolos/lib/assets/stream.py
toolos/lib/assets/super.py
toolos-3.3.5.dist-info/METADATA
toolos-3.3.5.dist-info/WHEEL
toolos-3.3.5.dist-info/top_level.txt
toolos-3.3.5.dist-info/RECORD
