Metadata-Version: 2.4
Name: toolos
Version: 3.3.5
Summary: A very Usefull API-Framework for All-Type Python Projects
Author-email: Lilias <lilias.ge@gmail.com>
License: MIT
Classifier: Development Status :: 4 - Beta
Classifier: Intended Audience :: Developers
Classifier: License :: OSI Approved :: MIT License
Classifier: Programming Language :: Python :: 3
Classifier: Programming Language :: Python :: 3.12
Classifier: Topic :: Software Development :: Libraries :: Python Modules
Classifier: Topic :: Software Development :: User Interfaces
Classifier: Topic :: Games/Entertainment
Classifier: Operating System :: OS Independent
Requires-Python: >=3.12
Requires-Dist: PyQt6>=6.4.0
Requires-Dist: ursina>=5.2.0
Requires-Dist: numpy>=1.24.0
Requires-Dist: pillow>=9.3.0
